LICENSE
README.md
setup.py
mkdocs_obsidian_support_plugin.egg-info/PKG-INFO
mkdocs_obsidian_support_plugin.egg-info/SOURCES.txt
mkdocs_obsidian_support_plugin.egg-info/dependency_links.txt
mkdocs_obsidian_support_plugin.egg-info/entry_points.txt
mkdocs_obsidian_support_plugin.egg-info/requires.txt
mkdocs_obsidian_support_plugin.egg-info/top_level.txt
obsidian_support/__init__.py
obsidian_support/plugin.py
obsidian_support/conversion/__init__.py
obsidian_support/conversion/abstract_conversion.py
obsidian_support/conversion/util.py
obsidian_support/conversion/admonition/__init__.py
obsidian_support/conversion/admonition/admonition_backquotes.py
obsidian_support/conversion/admonition/admonition_callout.py
obsidian_support/conversion/comment/__init__.py
obsidian_support/conversion/comment/comment.py
obsidian_support/conversion/image_link/__init__.py
obsidian_support/conversion/image_link/image_internal_link.py
obsidian_support/conversion/image_link/image_web_link.py
obsidian_support/conversion/pdf/__init__.py
obsidian_support/conversion/pdf/pdf.py
obsidian_support/conversion/tabs/__init__.py
obsidian_support/conversion/tabs/tabs_backquotes.py
obsidian_support/conversion/tabs/tabs_tilde_block.py
obsidian_support/conversion/tags/__init__.py
obsidian_support/conversion/tags/tags.py
test/__init__.py
test/test_conversions.py
test/conversion/__init__.py
test/conversion/test_util.py
test/conversion/admonition/__init__.py
test/conversion/admonition/test_admonition_backquotes.py
test/conversion/admonition/test_admonition_callout.py
test/conversion/tabs/__init__.py
test/conversion/tabs/test_tabs_backquotes.py
test/conversion/tags/__init__.py
test/conversion/tags/test_tags.py